pre_verilog/test_learning/expression.v
`timescale 1ns / 1ps
//////////////////////////////////////////////////////////////////////////////////
// Company: 
// Engineer: 
// 
// Create Date:    15:09:24 10/18/2025 
// Design Name: 
// Module Name:    expression 
// Project Name: 
// Target Devices: 
// Tool versions: 
// Description: 
//
// Dependencies: 
//
// Revision: 
// Revision 0.01 - File Created
// Additional Comments: 
//
//////////////////////////////////////////////////////////////////////////////////
module expression(
    input clk,
    input clr,
    input [7:0] in,
    output reg out
);
// IDLE ONE_NUM NUM_WITH_ONEOP VAILD INVALID
    parameter  IDLE = 3'b000,
        ONE_NUM = 3'b001,
        NUM_WITH_ONEOP = 3'b010,
        VAILD = 3'b011, 
        INVALID = 3'b100; // 异常符号、连续数字、前导运算符、连续运算符
    
    // machine variable
    reg [2:0] st_cur;
    reg [2:0] st_next;

    // 时序逻辑
    always @(posedge clk or posedge clr) begin
        if(clr)begin
            st_cur <= IDLE;
            //out <= 0;
        end
        else st_cur <= st_next; //!debug2
    end

    //状态转移和输出 MOORE
    always @(*) begin
        case (st_cur)
            IDLE: 
                begin
                    out = 0; //处理输出逻辑
                    case(in) //处理状态转移
                        "0", "1", "2", "3", "4", "5", "6", "7", "8", "9":  st_next = ONE_NUM;
                        "+" : st_next = INVALID;
                        "*" : st_next = INVALID;
                        default: st_next = INVALID; //!debug1 因为可能会输入其他字符
                    endcase
                end
            ONE_NUM:
                begin
                    out = 1;
                    case(in)
                        "0", "1", "2", "3", "4", "5", "6", "7", "8", "9":  st_next = INVALID;
                        "+", "*" : st_next = NUM_WITH_ONEOP;
                        default: st_next = INVALID;                        
                    endcase
                end
            NUM_WITH_ONEOP:
                begin       
                    out = 0;
                    case(in)
                        "0", "1", "2", "3", "4", "5", "6", "7", "8", "9":  st_next = VAILD;
                        "+", "*" : st_next = INVALID;
                        default: st_next = INVALID; 
                    endcase
                end
            VAILD:  
                begin
                    out = 1;
                    case(in)
                        "0", "1", "2", "3", "4", "5", "6", "7", "8", "9":  st_next = INVALID; //连续数字异常
                        "+", "*" : st_next = NUM_WITH_ONEOP;  
                        default: st_next = INVALID;                      
                    endcase
                end
            INVALID:    
                begin
                    out = 0;
                    case(in)
                        "0", "1", "2", "3", "4", "5", "6", "7", "8", "9":  st_next = INVALID; //重新开始
                        "+", "*" : st_next = INVALID; 
                        default: st_next = INVALID;                      
                    endcase  
                end
            default: //!default added for safety
                begin
                    out = 0;
                    st_next = IDLE;
                end
        endcase
    end   



endmodule

pre_verilog/test_learning/expr_tb.v
`timescale 1ns / 1ps

////////////////////////////////////////////////////////////////////////////////
// Company: 
// Engineer:
//
// Create Date:   15:10:12 10/18/2025
// Design Name:   expression
// Module Name:   C:/Users/27628/Desktop/CO-2025/pre_verilog/test_learning/expr_tb.v
// Project Name:  test_learning
// Target Device:  
// Tool versions:  
// Description: 
//
// Verilog Test Fixture created by ISE for module: expression
//
// Dependencies:
// 
// Revision:
// Revision 0.01 - File Created
// Additional Comments:
// 
////////////////////////////////////////////////////////////////////////////////

`timescale 1ns/1ps

module expr_tb;

    reg clk;
    reg clr;
    reg [7:0] in;
    wire out;

    // 实例化被测模块
    expression uut (
        .clk(clk),
        .clr(clr),
        .in(in),
        .out(out)
    );

    // 时钟周期 10ns
    always #5 clk = ~clk;

    // 任务：发送单个字符
    task send_char;
        input [7:0] ch;
        begin
            in = ch;
            #10; // 等待一个时钟周期
            //$display("[%0t] input=%s (ascii=%0d) -> out=%0d", $time, ch, ch, out);
        end
    endtask
    
    initial begin
        $dumpfile("expr_tb.vcd");  // 生成波形文件
        $dumpvars(0, expr_tb);     // 记录所有信号（包括子模块）
    end

    // 测试主过程
    initial begin
        $display("==== Expr FSM Testbench ====");
        clk = 0;
        clr = 0;
        in = 0;

        // 复位
        clr = 1;
        #10;
        clr = 0;

        // ==== 测试 1: 合法表达式 1+2 ====
                $display("\n==== Test 1: 1+2 ====");
        send_char("1");
        send_char("+");
        send_char("2");

        // ==== 测试 2: 非法表达式 1++2 ====
        $display("\n==== Test 2: 1++2 ====");
        clr = 1; #10; clr = 0; // 清零重新开始
        @(negedge clk) ;
        send_char("1");
        send_char("+");
        send_char("+");
        send_char("2");

        // ==== 测试 3: 前导运算符 +2 ====
        $display("\n==== Test 3: +2 ====");
        clr = 1; #10; clr = 0;
        @(negedge clk) ;
        send_char("+");
        send_char("2");

        // ==== 测试 4: 连续数字 12 ====
        $display("\n==== Test 4: 12 ====");
        clr = 1; #10; clr = 0;
        @(negedge clk) ;
        send_char("1");
        send_char("2");

        // ==== 测试 5: 1*3+5 ====
        $display("\n==== Test 5: 1*3+5 ====");
        clr = 1; #10; clr = 0;
        @(negedge clk) ;
        send_char("1");
        send_char("*");
        send_char("3");
        send_char("+");
        send_char("5");

        // ==== 结束 ====
        $display("\n==== Testbench Finished ====");
        #20;
        $stop;
    end

endmodule

pre_verilog/test_learning/expr_tb.vcd
$date
   Sat Oct 18 15:41:28 2025
$end
$version
  P.20131013
$end
$timescale
  1ps
$end
$scope module expr_tb $end
$var wire 1 ! out $end
$var reg 1 " clk $end
$var reg 1 # clr $end
$var reg 8 $ in [7:0] $end
$scope task send_char $end
$var reg 8 % ch [7:0] $end
$upscope $end
$scope module uut $end
$var wire 1 & clk $end
$var wire 1 ' clr $end
$var wire 1 ( in [7] $end
$var wire 1 ) in [6] $end
$var wire 1 * in [5] $end
$var wire 1 + in [4] $end
$var wire 1 , in [3] $end
$var wire 1 - in [2] $end
$var wire 1 . in [1] $end
$var wire 1 / in [0] $end
$var reg 1 0 out $end
$var reg 3 1 st_cur [2:0] $end
$var reg 3 2 st_next [2:0] $end
$upscope $end
$upscope $end
$enddefinitions $end
#0
$dumpvars
0/
1'
0!
0,
0(
0)
0+
0*
0-
0.
0"
1#
b0 $
bx %
00
b0 1
b100 2
0&
$end
#5000
1"
1&
#10000
1/
0'
1+
1*
0"
0#
b110001 $
b110001 %
b1 2
0&
#15000
1!
1"
10
b1 1
b100 2
1&
#20000
1,
0+
1.
0"
b101011 $
b101011 %
b10 2
0&
#25000
0!
1"
00
b10 1
b100 2
1&
#30000
0/
0,
1+
0"
b110010 $
b110010 %
b11 2
0&
#35000
1!
1"
10
b11 1
b100 2
1&
#40000
1'
0!
0"
1#
00
b0 1
b1 2
0&
#45000
1"
1&
#50000
1/
0'
0.
0"
0#
b110001 $
b110001 %
0&
#55000
1!
1"
10
b1 1
b100 2
1&
#60000
1,
0+
1.
0"
b101011 $
b101011 %
b10 2
0&
#65000
0!
1"
00
b10 1
b100 2
1&
#70000
0"
0&
#75000
1"
b100 1
1&
#80000
0/
0,
1+
0"
b110010 $
b110010 %
0&
#85000
1"
1&
#90000
1'
0"
1#
b0 1
b1 2
0&
#95000
1"
1&
#100000
1/
0'
1,
0+
0"
0#
b101011 $
b101011 %
b100 2
0&
#105000
1"
b100 1
1&
#110000
0/
0,
1+
0"
b110010 $
b110010 %
0&
#115000
1"
1&
#120000
1'
0"
1#
b0 1
b1 2
0&
#125000
1"
1&
#130000
1/
0'
0.
0"
0#
b110001 $
b110001 %
0&
#135000
1!
1"
10
b1 1
b100 2
1&
#140000
0/
1.
0"
b110010 $
b110010 %
0&
#145000
0!
1"
00
b100 1
1&
#150000
1'
0"
1#
b0 1
b1 2
0&
#155000
1"
1&
#160000
1/
0'
0.
0"
0#
b110001 $
b110001 %
0&
#165000
1!
1"
10
b1 1
b100 2
1&
#170000
0/
1,
0+
1.
0"
b101010 $
b101010 %
b10 2
0&
#175000
0!
1"
00
b10 1
b100 2
1&
#180000
1/
0,
1+
0"
b110011 $
b110011 %
b11 2
0&
#185000
1!
1"
10
b11 1
b100 2
1&
#190000
1,
0+
0"
b101011 $
b101011 %
b10 2
0&
#195000
0!
1"
00
b10 1
b100 2
1&
#200000
0,
1+
1-
0.
0"
b110101 $
b110101 %
b11 2
0&
#205000
1!
1"
10
b11 1
b100 2
1&
#210000
0"
0&
#215000
0!
1"
00
b100 1
1&
